MANIFEST.in
README.rst
setup.py
dpcluster/__init__.py
dpcluster/algorithms.py
dpcluster/caching.py
dpcluster/distributions.py
dpcluster/gpu_exp.py
dpcluster/test.py
dpcluster.egg-info/PKG-INFO
dpcluster.egg-info/SOURCES.txt
dpcluster.egg-info/dependency_links.txt
dpcluster.egg-info/not-zip-safe
dpcluster.egg-info/requires.txt
dpcluster.egg-info/top_level.txt