Metadata-Version: 1.1
Name: dpcluster
Version: 0.104
Summary: dpcluster is a package for grouping together (clustering) vectors. It automatically chooses the number of clusters that fits the data best based on the underlying Dirichlet Process mixture model.
Home-page: http://dpcluster.readthedocs.org/
Author: Teodor Mihai Moldovan
Author-email: moldovan@cs.berkeley.edu
License: UNKNOWN
Download-URL: http://github.com/teodor-moldovan/dpcluster
Platform: UNKNOWN
Classifier: Topic :: Scientific/Engineering :: Artificial Intelligence
Classifier: Intended Audience :: Science/Research
Classifier: Intended Audience :: Developers
Classifier: Development Status :: 2 - Pre-Alpha
